[
  {
    "id": "2025-12-23-mortgage-rates-hold-steady-amidst-market-crosscurrents",
    "date": "2025-12-23T07:15:18.681336",
    "title": "Mortgage Rates Hold Steady Amidst Market Crosscurrents",
    "summary": "Mortgage rates are showing minimal movement, caught between positive inflation data and persistent market uncertainty.",
    "content": "## Market Pulse\n\nThe 30-year fixed mortgage rate remains relatively stable, hovering around 6.24% according to daily surveys, and 6.21% according to Freddie Mac, mirroring the 10-Year Treasury yield's sideways movement at 4.169%. This suggests a holding pattern in the mortgage market as the year comes to a close. The Federal Funds Rate remains at 3.88%, reflecting previous rate cuts.\n\n## Key Drivers\n\nThe current mortgage rate environment is influenced by two opposing forces. Recent news highlights that lower rates are a potential 'gift' for holiday homebuyers as inflation cools, and the market anticipates a less aggressive Federal Reserve. The latest CPI data supports this, showing continued, albeit slow, inflation decrease. However, other reports point to market uncertainty and persistent, if smaller, rate increases, keeping rates from falling dramatically. This mixed messaging creates a tug-of-war, preventing significant rate movement.\n\n## Outlook\n\nLooking ahead, the direction of mortgage rates remains uncertain. While the expectation of future Federal Reserve rate cuts in late 2024 or early 2025 could put downward pressure on rates, ongoing market volatility and economic uncertainty may limit any significant declines. Homeowners and prospective buyers should closely monitor inflation data and Federal Reserve policy announcements to gauge future rate movements. The near-term outlook suggests continued stability with a slight downward bias, but be prepared for potential volatility. ",
    "tags": [
      "mortgage",
      "market-update"
    ]
  },
  {
    "id": "123-placeholder",
    "date": "2025-12-21T08:00:00",
    "title": "Mortgage Rates Hold Steady Amid Holiday Calm",
    "summary": "Rates remain flat as markets wind down for the year, with the 10-year Treasury showing little movement.",
    "content": "## Market Pulse\n\nMortgage rates are **flat** today, hovering around 6.5% for the 30-year fixed. The 10-year Treasury yield, a primary driver of mortgage rates, has settled near 3.9%, indicating a stable environment as we approach the holiday weekend.\n\n## Key Drivers\n\n*   **Holiday Volume:** Trading volume is thin, leading to less volatility.\n*   **Economic Data:** No major economic reports were released today, leaving the market without a strong catalyst for change.\n\n## Outlook\n\nExpect rates to remain range-bound through the end of the year unless unexpected geopolitical news emerges.",
    "tags": [
      "mortgage",
      "rates",
      "update"
    ]
  }
]